aind_airflow_jobs/__init__.py
aind_airflow_jobs/alert_handler.py
aind_airflow_jobs/hpc_handler.py
aind_airflow_jobs/log_handler.py
aind_airflow_jobs/slurm_handler.py
aind_airflow_jobs/task_handler.py
aind_airflow_jobs-0.2.7.dist-info/licenses/LICENSE
aind_airflow_jobs-0.2.7.dist-info/METADATA
aind_airflow_jobs-0.2.7.dist-info/WHEEL
aind_airflow_jobs-0.2.7.dist-info/top_level.txt
aind_airflow_jobs-0.2.7.dist-info/RECORD
