Metadata-Version: 2.4
Name: aind-airflow-jobs
Version: 0.2.7
Summary: Global classes for AIND Airflow service
Author: Allen Institute for Neural Dynamics
License: MIT
Classifier: Programming Language :: Python :: 3
Requires-Python: >=3.8
License-File: LICENSE
Requires-Dist: pydantic-settings<3.0,>=2.2.0
Requires-Dist: pydantic<3.0,>=2.2.0
Provides-Extra: dev
Requires-Dist: aind-airflow-jobs[all]; extra == "dev"
Requires-Dist: black; extra == "dev"
Requires-Dist: coverage; extra == "dev"
Requires-Dist: flake8; extra == "dev"
Requires-Dist: interrogate; extra == "dev"
Requires-Dist: isort; extra == "dev"
Requires-Dist: Sphinx; extra == "dev"
Requires-Dist: furo; extra == "dev"
Provides-Extra: all
Requires-Dist: aind-airflow-jobs[airflow]; extra == "all"
Requires-Dist: aind-airflow-jobs[loki]; extra == "all"
Requires-Dist: aind-airflow-jobs[slurm]; extra == "all"
Provides-Extra: airflow
Requires-Dist: google-re2==1.0; extra == "airflow"
Requires-Dist: apache-airflow==2.8.1; extra == "airflow"
Requires-Dist: apache-airflow-providers-ssh<=3.14.0,>=3.13.1; extra == "airflow"
Provides-Extra: loki
Requires-Dist: python-logging-loki==0.3.1; extra == "loki"
Provides-Extra: slurm
Requires-Dist: aind-slurm-rest==1.0.3; extra == "slurm"
Dynamic: license-file
